pyams_content_api/__init__.py
pyams_content_api/include.py
pyams_content_api/interfaces.py
pyams_content_api/component/__init__.py
pyams_content_api/component/association.py
pyams_content_api/component/cards.py
pyams_content_api/component/contact.py
pyams_content_api/component/extfile.py
pyams_content_api/component/frame.py
pyams_content_api/component/gallery.py
pyams_content_api/component/keynumber.py
pyams_content_api/component/links.py
pyams_content_api/component/map.py
pyams_content_api/component/thesaurus.py
pyams_content_api/component/verbatim.py
pyams_content_api/component/video.py
pyams_content_api/component/illustration/__init__.py
pyams_content_api/component/illustration/schema.py
pyams_content_api/component/paragraph/__init__.py
pyams_content_api/component/paragraph/html.py
pyams_content_api/doctests/README.rst
pyams_content_api/feature/__init__.py
pyams_content_api/feature/json/__init__.py
pyams_content_api/feature/json/interfaces.py
pyams_content_api/locales/pyams_content_api.pot
pyams_content_api/locales/fr/LC_MESSAGES/pyams_content_api.mo
pyams_content_api/locales/fr/LC_MESSAGES/pyams_content_api.po
pyams_content_api/reference/__init__.py
pyams_content_api/reference/pictogram.py
pyams_content_api/shared/__init__.py
pyams_content_api/shared/common/__init__.py
pyams_content_api/shared/common/interfaces.py
pyams_content_api/shared/common/schema.py
pyams_content_api/shared/common/workflow.py
pyams_content_api/shared/common/api/__init__.py
pyams_content_api/tests/__init__.py
pyams_content_api/tests/test_utilsdocs.py
pyams_content_api/tests/test_utilsdocstrings.py
pyams_content_api-2.2.1.dist-info/LICENSE
pyams_content_api-2.2.1.dist-info/METADATA
pyams_content_api-2.2.1.dist-info/WHEEL
pyams_content_api-2.2.1.dist-info/namespace_packages.txt
pyams_content_api-2.2.1.dist-info/top_level.txt
pyams_content_api-2.2.1.dist-info/RECORD
