Metadata-Version: 2.1
Name: pyams-content-api
Version: 2.2.1
Summary: PyAMS content REST API components
Home-page: https://pyams.readthedocs.io
Author: Thierry Florac
Author-email: tflorac@ulthar.net
License: ZPL
Keywords: Pyramid PyAMS
Classifier: License :: OSI Approved :: Zope Public License
Classifier: Development Status :: 4 - Beta
Classifier: Programming Language :: Python
Classifier: Framework :: Pyramid
Classifier: Topic :: Software Development :: Libraries :: Python Modules
License-File: LICENSE
Requires-Dist: setuptools
Requires-Dist: colander
Requires-Dist: cornice
Requires-Dist: pyams-content
Requires-Dist: pyams-file
Requires-Dist: pyams-i18n
Requires-Dist: pyams-security
Requires-Dist: pyams-sequence
Requires-Dist: pyams-utils
Requires-Dist: pyams-workflow
Requires-Dist: pyramid
Requires-Dist: zope.interface
Provides-Extra: test
Requires-Dist: pyramid-zcml ; extra == 'test'
Requires-Dist: zope.exceptions ; extra == 'test'
